LICENSE
README.md
pyproject.toml
setup.py
./misuma/__init__.py
misuma.egg-info/PKG-INFO
misuma.egg-info/SOURCES.txt
misuma.egg-info/dependency_links.txt
misuma.egg-info/entry_points.txt
misuma.egg-info/requires.txt
misuma.egg-info/top_level.txt