Metadata-Version: 2.1
Name: misuma
Version: 0.6.1
Summary: Sum two numbers
Home-page: https://pypi.org/project/misuma
Author: Bang1329
Author-email: santiago.hg2292@gmail.com
License: MIT
Keywords: Sum Addition
Platform: UNKNOWN
Classifier: Programming Language :: Python :: 3
Classifier: License :: OSI Approved :: MIT License
Classifier: Operating System :: OS Independent
License-File: LICENSE
